{
    "repository_address_display": [
        "http://fedoraproxy.lib.virginia.edu/fedora"
    ], 
    "library_facet": [
        "Special Collections"
    ], 
    "date_received_facet": "2013061117", 
    "extra": {
        "safeSearchAnnotation": {
            "medical": "VERY_UNLIKELY", 
            "violence": "VERY_UNLIKELY", 
            "spoof": "VERY_UNLIKELY", 
            "adult": "VERY_UNLIKELY"
        }, 
        "textAnnotations": [
            {
                "locale": "sq", 
                "description": "1AdULU tha ) iii : 1 M 1 AHW11)IU\u4ece1311\u51c6E MIRe\n", 
                "boundingPoly": {
                    "vertices": [
                        {
                            "y": 1187, 
                            "x": 583
                        }, 
                        {
                            "y": 1187, 
                            "x": 1664
                        }, 
                        {
                            "y": 1331, 
                            "x": 1664
                        }, 
                        {
                            "y": 1331, 
                            "x": 583
                        }
                    ]
                }
            }
        ], 
        "labelAnnotations": [
            {
                "score": 0.93418366, 
                "mid": "/m/038t8_", 
                "description": "estate"
            }, 
            {
                "score": 0.80319029, 
                "mid": "/m/03jm5", 
                "description": "house"
            }, 
            {
                "score": 0.80053204, 
                "mid": "/m/01l0mw", 
                "description": "home"
            }, 
            {
                "score": 0.8, 
                "mid": "/m/080sjd", 
                "description": "farmhouse"
            }, 
            {
                "score": 0.67513996, 
                "mid": "/m/0cgh4", 
                "description": "building"
            }
        ], 
        "imagePropertiesAnnotation": {
            "dominantColors": {
                "colors": [
                    {
                        "color": {
                            "blue": 156, 
                            "green": 156, 
                            "red": 156
                        }, 
                        "pixelFraction": 0.2267433, 
                        "score": 0.48943803
                    }, 
                    {
                        "color": {
                            "blue": 16, 
                            "green": 16, 
                            "red": 16
                        }, 
                        "pixelFraction": 0.015632184, 
                        "score": 0.094353087
                    }, 
                    {
                        "color": {
                            "blue": 124, 
                            "green": 124, 
                            "red": 124
                        }, 
                        "pixelFraction": 0.062375478, 
                        "score": 0.12011968
                    }, 
                    {
                        "color": {
                            "blue": 188, 
                            "green": 188, 
                            "red": 188
                        }, 
                        "pixelFraction": 0.22068965, 
                        "score": 0.11782199
                    }, 
                    {
                        "color": {
                            "blue": 51, 
                            "green": 51, 
                            "red": 51
                        }, 
                        "pixelFraction": 0.024980843, 
                        "score": 0.082396358
                    }, 
                    {
                        "color": {
                            "blue": 84, 
                            "green": 84, 
                            "red": 84
                        }, 
                        "pixelFraction": 0.035325669, 
                        "score": 0.060381033
                    }, 
                    {
                        "color": {
                            "blue": 232, 
                            "green": 232, 
                            "red": 232
                        }, 
                        "pixelFraction": 0.41425288, 
                        "score": 0.03548982
                    }
                ]
            }
        }
    }, 
    "content_model_facet": [
        "jp2k"
    ], 
    "author_facet": [
        "Davis, Jackson, 1882-1947"
    ], 
    "media_description_display": [
        "Full view"
    ], 
    "source_facet": [
        "UVA Library Digital Repository"
    ], 
    "author_display": [
        "Davis, Jackson, 1882-1947"
    ], 
    "main_title_display": [
        "Morehouse Public/Parish Training School (Dormitory)"
    ], 
    "score": 1.0, 
    "call_number_display": [
        "MSS 3072, 3072-a"
    ], 
    "digital_collection_facet": [
        "The Jackson Davis Collection of African American Photographs"
    ], 
    "id": "uva-lib:330834", 
    "year_display": [
        "1921-03-19"
    ], 
    "marc_display_facet": [
        "false"
    ], 
    "title_display": [
        "Morehouse Public/Parish Training School (Dormitory)"
    ], 
    "format_facet": [
        "Online", 
        "Visual Materials", 
        "Photograph"
    ]
}