{
    "author_display": [
        "Davis, Jackson, 1882-1947"
    ], 
    "library_facet": [
        "Special Collections"
    ], 
    "date_received_facet": "2013061117", 
    "extra": {
        "faceAnnotations": [
            {
                "panAngle": -2.0754271, 
                "landmarkingConfidence": 0.51512867, 
                "detectionConfidence": 0.83214605, 
                "tiltAngle": -1.3939375, 
                "joyLikelihood": "VERY_UNLIKELY", 
                "landmarks": [
                    {
                        "position": {
                            "y": 1009.8325, 
                            "x": 1907.4403, 
                            "z": -0.0012114688
                        }, 
                        "type": "LEFT_EYE"
                    }, 
                    {
                        "position": {
                            "y": 1012.2246, 
                            "x": 1978.1184, 
                            "z": -2.5474398
                        }, 
                        "type": "RIGHT_EYE"
                    }, 
                    {
                        "position": {
                            "y": 993.1355, 
                            "x": 1882.5787, 
                            "z": 7.4084024
                        }, 
                        "type": "LEFT_OF_LEFT_EYEBROW"
                    }, 
                    {
                        "position": {
                            "y": 994.11261, 
                            "x": 1924.629, 
                            "z": -14.948459
                        }, 
                        "type": "RIGHT_OF_LEFT_EYEBROW"
                    }, 
                    {
                        "position": {
                            "y": 995.78027, 
                            "x": 1959.2172, 
                            "z": -16.192287
                        }, 
                        "type": "LEFT_OF_RIGHT_EYEBROW"
                    }, 
                    {
                        "position": {
                            "y": 998.19977, 
                            "x": 2002.1864, 
                            "z": 2.8159916
                        }, 
                        "type": "RIGHT_OF_RIGHT_EYEBROW"
                    }, 
                    {
                        "position": {
                            "y": 1009.7483, 
                            "x": 1940.833, 
                            "z": -16.257309
                        }, 
                        "type": "MIDPOINT_BETWEEN_EYES"
                    }, 
                    {
                        "position": {
                            "y": 1048.5374, 
                            "x": 1937.8506, 
                            "z": -35.977425
                        }, 
                        "type": "NOSE_TIP"
                    }, 
                    {
                        "position": {
                            "y": 1077.4243, 
                            "x": 1936.9644, 
                            "z": -18.780695
                        }, 
                        "type": "UPPER_LIP"
                    }, 
                    {
                        "position": {
                            "y": 1101.2888, 
                            "x": 1936.2449, 
                            "z": -12.943674
                        }, 
                        "type": "LOWER_LIP"
                    }, 
                    {
                        "position": {
                            "y": 1085.1501, 
                            "x": 1908.8607, 
                            "z": 1.8775804
                        }, 
                        "type": "MOUTH_LEFT"
                    }, 
                    {
                        "position": {
                            "y": 1087.7778, 
                            "x": 1966.1241, 
                            "z": -0.16421109
                        }, 
                        "type": "MOUTH_RIGHT"
                    }, 
                    {
                        "position": {
                            "y": 1088.675, 
                            "x": 1936.8191, 
                            "z": -13.130239
                        }, 
                        "type": "MOUTH_CENTER"
                    }, 
                    {
                        "position": {
                            "y": 1057.0742, 
                            "x": 1957.6311, 
                            "z": -9.3852062
                        }, 
                        "type": "NOSE_BOTTOM_RIGHT"
                    }, 
                    {
                        "position": {
                            "y": 1056.6254, 
                            "x": 1918.3951, 
                            "z": -7.6186423
                        }, 
                        "type": "NOSE_BOTTOM_LEFT"
                    }, 
                    {
                        "position": {
                            "y": 1061.5635, 
                            "x": 1937.229, 
                            "z": -19.469498
                        }, 
                        "type": "NOSE_BOTTOM_CENTER"
                    }, 
                    {
                        "position": {
                            "y": 1004.8215, 
                            "x": 1906.0492, 
                            "z": -4.8504605
                        }, 
                        "type": "LEFT_EYE_TOP_BOUNDARY"
                    }, 
                    {
                        "position": {
                            "y": 1010.8794, 
                            "x": 1920.8953, 
                            "z": -0.20019133
                        }, 
                        "type": "LEFT_EYE_RIGHT_CORNER"
                    }, 
                    {
                        "position": {
                            "y": 1014.1111, 
                            "x": 1906.5621, 
                            "z": -0.46613178
                        }, 
                        "type": "LEFT_EYE_BOTTOM_BOUNDARY"
                    }, 
                    {
                        "position": {
                            "y": 1008.9503, 
                            "x": 1892.0867, 
                            "z": 7.1402535
                        }, 
                        "type": "LEFT_EYE_LEFT_CORNER"
                    }, 
                    {
                        "position": {
                            "y": 1009.6061, 
                            "x": 1904.7607, 
                            "z": -1.6505642
                        }, 
                        "type": "LEFT_EYE_PUPIL"
                    }, 
                    {
                        "position": {
                            "y": 1008.7114, 
                            "x": 1977.2637, 
                            "z": -7.4187107
                        }, 
                        "type": "RIGHT_EYE_TOP_BOUNDARY"
                    }, 
                    {
                        "position": {
                            "y": 1014.4023, 
                            "x": 1991.4872, 
                            "z": 3.5101507
                        }, 
                        "type": "RIGHT_EYE_RIGHT_CORNER"
                    }, 
                    {
                        "position": {
                            "y": 1017.671, 
                            "x": 1977.093, 
                            "z": -2.9859335
                        }, 
                        "type": "RIGHT_EYE_BOTTOM_BOUNDARY"
                    }, 
                    {
                        "position": {
                            "y": 1013.8881, 
                            "x": 1964.7795, 
                            "z": -1.6388757
                        }, 
                        "type": "RIGHT_EYE_LEFT_CORNER"
                    }, 
                    {
                        "position": {
                            "y": 1013.6219, 
                            "x": 1977.8468, 
                            "z": -4.3521247
                        }, 
                        "type": "RIGHT_EYE_PUPIL"
                    }, 
                    {
                        "position": {
                            "y": 984.11017, 
                            "x": 1903.894, 
                            "z": -8.859951
                        }, 
                        "type": "LEFT_EYEBROW_UPPER_MIDPOINT"
                    }, 
                    {
                        "position": {
                            "y": 988.30359, 
                            "x": 1981.1787, 
                            "z": -11.641767
                        }, 
                        "type": "RIGHT_EYEBROW_UPPER_MIDPOINT"
                    }, 
                    {
                        "position": {
                            "y": 1040.2883, 
                            "x": 1862.0704, 
                            "z": 90.671532
                        }, 
                        "type": "LEFT_EAR_TRAGION"
                    }, 
                    {
                        "position": {
                            "y": 1048.428, 
                            "x": 2023.5819, 
                            "z": 84.497459
                        }, 
                        "type": "RIGHT_EAR_TRAGION"
                    }, 
                    {
                        "position": {
                            "y": 994.0271, 
                            "x": 1941.8059, 
                            "z": -18.293419
                        }, 
                        "type": "FOREHEAD_GLABELLA"
                    }, 
                    {
                        "position": {
                            "y": 1133.0371, 
                            "x": 1934.8763, 
                            "z": -2.0344725
                        }, 
                        "type": "CHIN_GNATHION"
                    }, 
                    {
                        "position": {
                            "y": 1086.9445, 
                            "x": 1866.353, 
                            "z": 62.419857
                        }, 
                        "type": "CHIN_LEFT_GONION"
                    }, 
                    {
                        "position": {
                            "y": 1094.8979, 
                            "x": 2012.5555, 
                            "z": 57.108013
                        }, 
                        "type": "CHIN_RIGHT_GONION"
                    }
                ], 
                "sorrowLikelihood": "VERY_UNLIKELY", 
                "blurredLikelihood": "VERY_UNLIKELY", 
                "underExposedLikelihood": "VERY_UNLIKELY", 
                "angerLikelihood": "VERY_UNLIKELY", 
                "boundingPoly": {
                    "vertices": [
                        {
                            "y": 886, 
                            "x": 1824
                        }, 
                        {
                            "y": 886, 
                            "x": 2060
                        }, 
                        {
                            "y": 1160, 
                            "x": 2060
                        }, 
                        {
                            "y": 1160, 
                            "x": 1824
                        }
                    ]
                }, 
                "rollAngle": 3.0607853, 
                "headwearLikelihood": "VERY_UNLIKELY", 
                "surpriseLikelihood": "VERY_UNLIKELY", 
                "fdBoundingPoly": {
                    "vertices": [
                        {
                            "y": 954, 
                            "x": 1852
                        }, 
                        {
                            "y": 954, 
                            "x": 2027
                        }, 
                        {
                            "y": 1129, 
                            "x": 2027
                        }, 
                        {
                            "y": 1129, 
                            "x": 1852
                        }
                    ]
                }
            }, 
            {
                "panAngle": -8.6040668, 
                "landmarkingConfidence": 0.2725572, 
                "detectionConfidence": 0.51677221, 
                "tiltAngle": 8.8425465, 
                "joyLikelihood": "VERY_UNLIKELY", 
                "landmarks": [
                    {
                        "position": {
                            "y": 968.48022, 
                            "x": 1238.4034, 
                            "z": -0.00022286267
                        }, 
                        "type": "LEFT_EYE"
                    }, 
                    {
                        "position": {
                            "y": 955.19495, 
                            "x": 1309.2147, 
                            "z": -10.619169
                        }, 
                        "type": "RIGHT_EYE"
                    }, 
                    {
                        "position": {
                            "y": 955.63135, 
                            "x": 1213.4192, 
                            "z": 12.844872
                        }, 
                        "type": "LEFT_OF_LEFT_EYEBROW"
                    }, 
                    {
                        "position": {
                            "y": 945.53174, 
                            "x": 1251.4598, 
                            "z": -13.735682
                        }, 
                        "type": "RIGHT_OF_LEFT_EYEBROW"
                    }, 
                    {
                        "position": {
                            "y": 939.62512, 
                            "x": 1285.6438, 
                            "z": -18.930811
                        }, 
                        "type": "LEFT_OF_RIGHT_EYEBROW"
                    }, 
                    {
                        "position": {
                            "y": 935.23889, 
                            "x": 1330.925, 
                            "z": -4.9746561
                        }, 
                        "type": "RIGHT_OF_RIGHT_EYEBROW"
                    }, 
                    {
                        "position": {
                            "y": 957.4892, 
                            "x": 1270.6782, 
                            "z": -19.708914
                        }, 
                        "type": "MIDPOINT_BETWEEN_EYES"
                    }, 
                    {
                        "position": {
                            "y": 993.51965, 
                            "x": 1273.7864, 
                            "z": -46.509918
                        }, 
                        "type": "NOSE_TIP"
                    }, 
                    {
                        "position": {
                            "y": 1023.4766, 
                            "x": 1279.8966, 
                            "z": -34.296482
                        }, 
                        "type": "UPPER_LIP"
                    }, 
                    {
                        "position": {
                            "y": 1047.9333, 
                            "x": 1284.4479, 
                            "z": -32.899174
                        }, 
                        "type": "LOWER_LIP"
                    }, 
                    {
                        "position": {
                            "y": 1040.8434, 
                            "x": 1257.4341, 
                            "z": -12.772278
                        }, 
                        "type": "MOUTH_LEFT"
                    }, 
                    {
                        "position": {
                            "y": 1032.3804, 
                            "x": 1312.4283, 
                            "z": -21.244696
                        }, 
                        "type": "MOUTH_RIGHT"
                    }, 
                    {
                        "position": {
                            "y": 1034.8116, 
                            "x": 1282.5691, 
                            "z": -30.726439
                        }, 
                        "type": "MOUTH_CENTER"
                    }, 
                    {
                        "position": {
                            "y": 1000.3306, 
                            "x": 1299.2837, 
                            "z": -23.140352
                        }, 
                        "type": "NOSE_BOTTOM_RIGHT"
                    }, 
                    {
                        "position": {
                            "y": 1007.2087, 
                            "x": 1258.6067, 
                            "z": -17.264647
                        }, 
                        "type": "NOSE_BOTTOM_LEFT"
                    }, 
                    {
                        "position": {
                            "y": 1007.075, 
                            "x": 1276.8013, 
                            "z": -32.17841
                        }, 
                        "type": "NOSE_BOTTOM_CENTER"
                    }, 
                    {
                        "position": {
                            "y": 962.08923, 
                            "x": 1236.7318, 
                            "z": -3.8699625
                        }, 
                        "type": "LEFT_EYE_TOP_BOUNDARY"
                    }, 
                    {
                        "position": {
                            "y": 965.64874, 
                            "x": 1252.595, 
                            "z": -1.8099217
                        }, 
                        "type": "LEFT_EYE_RIGHT_CORNER"
                    }, 
                    {
                        "position": {
                            "y": 974.11353, 
                            "x": 1238.231, 
                            "z": -1.2491344
                        }, 
                        "type": "LEFT_EYE_BOTTOM_BOUNDARY"
                    }, 
                    {
                        "position": {
                            "y": 971.07031, 
                            "x": 1225.4855, 
                            "z": 8.7268171
                        }, 
                        "type": "LEFT_EYE_LEFT_CORNER"
                    }, 
                    {
                        "position": {
                            "y": 967.50842, 
                            "x": 1236.8719, 
                            "z": -1.4227401
                        }, 
                        "type": "LEFT_EYE_PUPIL"
                    }, 
                    {
                        "position": {
                            "y": 949.75507, 
                            "x": 1307.1589, 
                            "z": -14.547177
                        }, 
                        "type": "RIGHT_EYE_TOP_BOUNDARY"
                    }, 
                    {
                        "position": {
                            "y": 953.859, 
                            "x": 1323.9059, 
                            "z": -6.2038193
                        }, 
                        "type": "RIGHT_EYE_RIGHT_CORNER"
                    }, 
                    {
                        "position": {
                            "y": 959.97546, 
                            "x": 1309.9617, 
                            "z": -11.897367
                        }, 
                        "type": "RIGHT_EYE_BOTTOM_BOUNDARY"
                    }, 
                    {
                        "position": {
                            "y": 957.64844, 
                            "x": 1294.1772, 
                            "z": -8.1753654
                        }, 
                        "type": "RIGHT_EYE_LEFT_CORNER"
                    }, 
                    {
                        "position": {
                            "y": 954.82843, 
                            "x": 1309.1136, 
                            "z": -12.469955
                        }, 
                        "type": "RIGHT_EYE_PUPIL"
                    }, 
                    {
                        "position": {
                            "y": 941.47357, 
                            "x": 1230.0355, 
                            "z": -3.6959589
                        }, 
                        "type": "LEFT_EYEBROW_UPPER_MIDPOINT"
                    }, 
                    {
                        "position": {
                            "y": 928.14215, 
                            "x": 1306.4053, 
                            "z": -15.292556
                        }, 
                        "type": "RIGHT_EYEBROW_UPPER_MIDPOINT"
                    }, 
                    {
                        "position": {
                            "y": 1020.6985, 
                            "x": 1213.9961, 
                            "z": 88.653214
                        }, 
                        "type": "LEFT_EAR_TRAGION"
                    }, 
                    {
                        "position": {
                            "y": 992.99609, 
                            "x": 1373.811, 
                            "z": 64.44101
                        }, 
                        "type": "RIGHT_EAR_TRAGION"
                    }, 
                    {
                        "position": {
                            "y": 941.34766, 
                            "x": 1267.9454, 
                            "z": -18.839329
                        }, 
                        "type": "FOREHEAD_GLABELLA"
                    }, 
                    {
                        "position": {
                            "y": 1081.0826, 
                            "x": 1290.9854, 
                            "z": -27.836687
                        }, 
                        "type": "CHIN_GNATHION"
                    }, 
                    {
                        "position": {
                            "y": 1061.3544, 
                            "x": 1223.5083, 
                            "z": 51.61121
                        }, 
                        "type": "CHIN_LEFT_GONION"
                    }, 
                    {
                        "position": {
                            "y": 1036.2615, 
                            "x": 1367.844, 
                            "z": 29.658354
                        }, 
                        "type": "CHIN_RIGHT_GONION"
                    }
                ], 
                "sorrowLikelihood": "VERY_UNLIKELY", 
                "blurredLikelihood": "VERY_UNLIKELY", 
                "underExposedLikelihood": "VERY_UNLIKELY", 
                "angerLikelihood": "VERY_UNLIKELY", 
                "boundingPoly": {
                    "vertices": [
                        {
                            "y": 843, 
                            "x": 1170
                        }, 
                        {
                            "y": 843, 
                            "x": 1408
                        }, 
                        {
                            "y": 1121, 
                            "x": 1408
                        }, 
                        {
                            "y": 1121, 
                            "x": 1170
                        }
                    ]
                }, 
                "rollAngle": -8.5857449, 
                "headwearLikelihood": "VERY_UNLIKELY", 
                "surpriseLikelihood": "VERY_UNLIKELY", 
                "fdBoundingPoly": {
                    "vertices": [
                        {
                            "y": 897, 
                            "x": 1184
                        }, 
                        {
                            "y": 897, 
                            "x": 1378
                        }, 
                        {
                            "y": 1091, 
                            "x": 1378
                        }, 
                        {
                            "y": 1091, 
                            "x": 1184
                        }
                    ]
                }
            }, 
            {
                "panAngle": 14.204584, 
                "landmarkingConfidence": 0.13705756, 
                "detectionConfidence": 0.51249158, 
                "tiltAngle": 7.8484125, 
                "joyLikelihood": "VERY_UNLIKELY", 
                "landmarks": [
                    {
                        "position": {
                            "y": 1094.0845, 
                            "x": 1028.6918, 
                            "z": 0.00012272822
                        }, 
                        "type": "LEFT_EYE"
                    }, 
                    {
                        "position": {
                            "y": 1091.7565, 
                            "x": 1090.1824, 
                            "z": 15.380817
                        }, 
                        "type": "RIGHT_EYE"
                    }, 
                    {
                        "position": {
                            "y": 1080.9546, 
                            "x": 1005.9393, 
                            "z": 2.5499706
                        }, 
                        "type": "LEFT_OF_LEFT_EYEBROW"
                    }, 
                    {
                        "position": {
                            "y": 1076.585, 
                            "x": 1046.4535, 
                            "z": -5.78599
                        }, 
                        "type": "RIGHT_OF_LEFT_EYEBROW"
                    }, 
                    {
                        "position": {
                            "y": 1075.4121, 
                            "x": 1076.2035, 
                            "z": 1.6693853
                        }, 
                        "type": "LEFT_OF_RIGHT_EYEBROW"
                    }, 
                    {
                        "position": {
                            "y": 1076.9342, 
                            "x": 1108.2295, 
                            "z": 28.188877
                        }, 
                        "type": "RIGHT_OF_RIGHT_EYEBROW"
                    }, 
                    {
                        "position": {
                            "y": 1089.1285, 
                            "x": 1062.4929, 
                            "z": -4.739212
                        }, 
                        "type": "MIDPOINT_BETWEEN_EYES"
                    }, 
                    {
                        "position": {
                            "y": 1122.1815, 
                            "x": 1069.5072, 
                            "z": -27.51301
                        }, 
                        "type": "NOSE_TIP"
                    }, 
                    {
                        "position": {
                            "y": 1147.3762, 
                            "x": 1067.7809, 
                            "z": -16.420628
                        }, 
                        "type": "UPPER_LIP"
                    }, 
                    {
                        "position": {
                            "y": 1169.2756, 
                            "x": 1068.3005, 
                            "z": -14.921718
                        }, 
                        "type": "LOWER_LIP"
                    }, 
                    {
                        "position": {
                            "y": 1159.4634, 
                            "x": 1040.2496, 
                            "z": -7.2972488
                        }, 
                        "type": "MOUTH_LEFT"
                    }, 
                    {
                        "position": {
                            "y": 1157.71, 
                            "x": 1088.3772, 
                            "z": 4.6906066
                        }, 
                        "type": "MOUTH_RIGHT"
                    }, 
                    {
                        "position": {
                            "y": 1157.7191, 
                            "x": 1067.6473, 
                            "z": -13.228463
                        }, 
                        "type": "MOUTH_CENTER"
                    }, 
                    {
                        "position": {
                            "y": 1129.751, 
                            "x": 1080.8514, 
                            "z": -0.59450942
                        }, 
                        "type": "NOSE_BOTTOM_RIGHT"
                    }, 
                    {
                        "position": {
                            "y": 1131.0242, 
                            "x": 1047.4318, 
                            "z": -8.96586
                        }, 
                        "type": "NOSE_BOTTOM_LEFT"
                    }, 
                    {
                        "position": {
                            "y": 1134.017, 
                            "x": 1066.8314, 
                            "z": -14.851429
                        }, 
                        "type": "NOSE_BOTTOM_CENTER"
                    }, 
                    {
                        "position": {
                            "y": 1089.136, 
                            "x": 1029.5939, 
                            "z": -3.43754
                        }, 
                        "type": "LEFT_EYE_TOP_BOUNDARY"
                    }, 
                    {
                        "position": {
                            "y": 1094.0542, 
                            "x": 1041.1692, 
                            "z": 3.3036468
                        }, 
                        "type": "LEFT_EYE_RIGHT_CORNER"
                    }, 
                    {
                        "position": {
                            "y": 1098.1677, 
                            "x": 1029.3665, 
                            "z": -1.0234786
                        }, 
                        "type": "LEFT_EYE_BOTTOM_BOUNDARY"
                    }, 
                    {
                        "position": {
                            "y": 1095.6096, 
                            "x": 1015.3928, 
                            "z": 2.5574467
                        }, 
                        "type": "LEFT_EYE_LEFT_CORNER"
                    }, 
                    {
                        "position": {
                            "y": 1093.8542, 
                            "x": 1028.3048, 
                            "z": -1.6528367
                        }, 
                        "type": "LEFT_EYE_PUPIL"
                    }, 
                    {
                        "position": {
                            "y": 1086.7125, 
                            "x": 1090.8496, 
                            "z": 11.918175
                        }, 
                        "type": "RIGHT_EYE_TOP_BOUNDARY"
                    }, 
                    {
                        "position": {
                            "y": 1092.2271, 
                            "x": 1100.9856, 
                            "z": 24.008728
                        }, 
                        "type": "RIGHT_EYE_RIGHT_CORNER"
                    }, 
                    {
                        "position": {
                            "y": 1095.78, 
                            "x": 1090.587, 
                            "z": 14.314283
                        }, 
                        "type": "RIGHT_EYE_BOTTOM_BOUNDARY"
                    }, 
                    {
                        "position": {
                            "y": 1092.8633, 
                            "x": 1077.8365, 
                            "z": 12.481924
                        }, 
                        "type": "RIGHT_EYE_LEFT_CORNER"
                    }, 
                    {
                        "position": {
                            "y": 1091.3745, 
                            "x": 1091.1854, 
                            "z": 14.027011
                        }, 
                        "type": "RIGHT_EYE_PUPIL"
                    }, 
                    {
                        "position": {
                            "y": 1070.5612, 
                            "x": 1026.3882, 
                            "z": -4.627377
                        }, 
                        "type": "LEFT_EYEBROW_UPPER_MIDPOINT"
                    }, 
                    {
                        "position": {
                            "y": 1067.9338, 
                            "x": 1092.8418, 
                            "z": 12.028785
                        }, 
                        "type": "RIGHT_EYEBROW_UPPER_MIDPOINT"
                    }, 
                    {
                        "position": {
                            "y": 1137.8958, 
                            "x": 973.9458, 
                            "z": 60.996769
                        }, 
                        "type": "LEFT_EAR_TRAGION"
                    }, 
                    {
                        "position": {
                            "y": 1132.4071, 
                            "x": 1113.0781, 
                            "z": 95.896942
                        }, 
                        "type": "RIGHT_EAR_TRAGION"
                    }, 
                    {
                        "position": {
                            "y": 1074.8829, 
                            "x": 1061.8243, 
                            "z": -4.2265296
                        }, 
                        "type": "FOREHEAD_GLABELLA"
                    }, 
                    {
                        "position": {
                            "y": 1198.6566, 
                            "x": 1068.2096, 
                            "z": -10.146184
                        }, 
                        "type": "CHIN_GNATHION"
                    }, 
                    {
                        "position": {
                            "y": 1173.7712, 
                            "x": 989.66467, 
                            "z": 32.433258
                        }, 
                        "type": "CHIN_LEFT_GONION"
                    }, 
                    {
                        "position": {
                            "y": 1168.8308, 
                            "x": 1115.403, 
                            "z": 63.955936
                        }, 
                        "type": "CHIN_RIGHT_GONION"
                    }
                ], 
                "sorrowLikelihood": "VERY_UNLIKELY", 
                "blurredLikelihood": "VERY_UNLIKELY", 
                "underExposedLikelihood": "VERY_UNLIKELY", 
                "angerLikelihood": "VERY_UNLIKELY", 
                "boundingPoly": {
                    "vertices": [
                        {
                            "y": 991, 
                            "x": 943
                        }, 
                        {
                            "y": 991, 
                            "x": 1152
                        }, 
                        {
                            "y": 1234, 
                            "x": 1152
                        }, 
                        {
                            "y": 1234, 
                            "x": 943
                        }
                    ]
                }, 
                "rollAngle": -4.2594414, 
                "headwearLikelihood": "VERY_UNLIKELY", 
                "surpriseLikelihood": "VERY_UNLIKELY", 
                "fdBoundingPoly": {
                    "vertices": [
                        {
                            "y": 1044, 
                            "x": 983
                        }, 
                        {
                            "y": 1044, 
                            "x": 1141
                        }, 
                        {
                            "y": 1202, 
                            "x": 1141
                        }, 
                        {
                            "y": 1202, 
                            "x": 983
                        }
                    ]
                }
            }
        ], 
        "safeSearchAnnotation": {
            "medical": "VERY_UNLIKELY", 
            "violence": "UNLIKELY", 
            "spoof": "VERY_UNLIKELY", 
            "adult": "VERY_UNLIKELY"
        }, 
        "textAnnotations": [
            {
                "locale": "en", 
                "description": "o:\nIT\n", 
                "boundingPoly": {
                    "vertices": [
                        {
                            "y": 1219, 
                            "x": 1756
                        }, 
                        {
                            "y": 1219, 
                            "x": 3478
                        }, 
                        {
                            "y": 2578, 
                            "x": 3478
                        }, 
                        {
                            "y": 2578, 
                            "x": 1756
                        }
                    ]
                }
            }
        ], 
        "labelAnnotations": [
            {
                "score": 0.9422558, 
                "mid": "/m/083jv", 
                "description": "white"
            }, 
            {
                "score": 0.94150215, 
                "mid": "/m/019sc", 
                "description": "black"
            }, 
            {
                "score": 0.88731045, 
                "mid": "/m/01g6gs", 
                "description": "black and white"
            }, 
            {
                "score": 0.58506364, 
                "mid": "/m/0ds4250", 
                "description": "groom"
            }, 
            {
                "score": 0.50850034, 
                "mid": "/m/016c4t", 
                "description": "ceremony"
            }
        ], 
        "imagePropertiesAnnotation": {
            "dominantColors": {
                "colors": [
                    {
                        "color": {
                            "blue": 249, 
                            "green": 249, 
                            "red": 249
                        }, 
                        "pixelFraction": 0.71725088, 
                        "score": 0.54689395
                    }, 
                    {
                        "color": {
                            "blue": 18, 
                            "green": 18, 
                            "red": 18
                        }, 
                        "pixelFraction": 0.029209621, 
                        "score": 0.080641761
                    }, 
                    {
                        "color": {
                            "blue": 194, 
                            "green": 194, 
                            "red": 194
                        }, 
                        "pixelFraction": 0.12529209, 
                        "score": 0.092527725
                    }, 
                    {
                        "color": {
                            "blue": 156, 
                            "green": 156, 
                            "red": 156
                        }, 
                        "pixelFraction": 0.05628866, 
                        "score": 0.08008182
                    }, 
                    {
                        "color": {
                            "blue": 52, 
                            "green": 52, 
                            "red": 52
                        }, 
                        "pixelFraction": 0.021580756, 
                        "score": 0.072632909
                    }, 
                    {
                        "color": {
                            "blue": 119, 
                            "green": 119, 
                            "red": 119
                        }, 
                        "pixelFraction": 0.026941581, 
                        "score": 0.063611634
                    }, 
                    {
                        "color": {
                            "blue": 83, 
                            "green": 83, 
                            "red": 83
                        }, 
                        "pixelFraction": 0.023436425, 
                        "score": 0.063610196
                    }
                ]
            }
        }
    }, 
    "content_model_facet": [
        "jp2k"
    ], 
    "media_description_display": [
        "Full view, women with baby in a room with an easel"
    ], 
    "source_facet": [
        "UVA Library Digital Repository"
    ], 
    "repository_address_display": [
        "http://fedoraproxy.lib.virginia.edu/fedora"
    ], 
    "main_title_display": [
        "Untitled photo: Africa and Middle East Misc."
    ], 
    "score": 1.0, 
    "call_number_display": [
        "MSS 3072, 3072-a"
    ], 
    "format_facet": [
        "Online", 
        "Visual Materials", 
        "Photograph"
    ], 
    "digital_collection_facet": [
        "The Jackson Davis Collection of African American Photographs"
    ], 
    "id": "uva-lib:332344", 
    "year_display": [
        "1915"
    ], 
    "marc_display_facet": [
        "false"
    ], 
    "title_display": [
        "Untitled photo: Africa and Middle East Misc."
    ], 
    "author_facet": [
        "Davis, Jackson, 1882-1947"
    ]
}